config_yourself/Config.py
config_yourself/__init__.py
config_yourself/exceptions.py
config_yourself/load.py
config_yourself/util.py
config_yourself/provider/__init__.py
config_yourself/provider/base.py
config_yourself/provider/datakey.py
config_yourself/provider/gpg.py
config_yourself/provider/kms.py
config_yourself/provider/password.py
tests/__init__.py
tests/conftest.py
config_yourself-1.0.2.dist-info/LICENSE
config_yourself-1.0.2.dist-info/METADATA
config_yourself-1.0.2.dist-info/NOTICE
config_yourself-1.0.2.dist-info/WHEEL
config_yourself-1.0.2.dist-info/top_level.txt
config_yourself-1.0.2.dist-info/RECORD
